MANIFEST.in
README.md
VERSION.txt
setup.cfg
setup.py
pyserver/__init__.py
pyserver/network/__init__.py
pyserver/network/async_controller.py
pyserver/network/async_multicast.py
pyserver/network/async_tcp_client.py
pyserver/network/async_tcp_server.py
pyserver/network/async_udp.py
pyserver/network/callback_interface.py
pyserver/network/preamble.py
pyserver/network/server_conf.py
pyserver/util/__init__.py
pyserver/util/enum.py
pyserver/util/or_event.py
pyserver/util/sig_terminate.py
pyserver/util/singleton.py
pyserver/util/subproc_controller.py
pyserver/util/timeout.py
pyserver/util/timer.py
pyserver3.egg-info/PKG-INFO
pyserver3.egg-info/SOURCES.txt
pyserver3.egg-info/dependency_links.txt
pyserver3.egg-info/requires.txt
pyserver3.egg-info/top_level.txt