Metadata-Version: 1.1
Name: pyserver3
Version: 0.1.8
Summary: TCP/UDP Aysnchronous Server/Client Library
Home-page: https://github.com/juhgiyo/pyserver3
Author: Woong Gyu La
Author-email: juhgiyo@gmail.com
License: The MIT License (MIT)
Keywords: tcp,udp,server,library
Platform: UNKNOWN
Classifier: Development Status :: 4 - Beta
Classifier: Programming Language :: Python :: 3.4
